mdpres.py
mdpres-0.1.0.dist-info/METADATA
mdpres-0.1.0.dist-info/WHEEL
mdpres-0.1.0.dist-info/entry_points.txt
mdpres-0.1.0.dist-info/RECORD
