Metadata-Version: 2.4
Name: mdpres
Version: 0.1.0
Summary: Markdown to HTML Presentation Generator
Project-URL: Homepage, https://github.com/yourusername/mdpres
Project-URL: Repository, https://github.com/yourusername/mdpres
Author-email: Your Name <your@email.com>
License-Expression: MIT
Keywords: html,markdown,mermaid,presentation,slides
Classifier: Development Status :: 4 - Beta
Classifier: Environment :: Console
Classifier: Intended Audience :: Developers
Classifier: License :: OSI Approved :: MIT License
Classifier: Programming Language :: Python :: 3
Classifier: Programming Language :: Python :: 3.11
Classifier: Programming Language :: Python :: 3.12
Classifier: Programming Language :: Python :: 3.13
Classifier: Topic :: Text Processing :: Markup :: Markdown
Requires-Python: >=3.11
